__init__.py
main.py
uvl/UVLCustomLexer.py
uvl/UVLPythonLexer.py
uvl/UVLPythonListener.py
uvl/UVLPythonParser.py
uvlparser-2.0.1.dist-info/METADATA
uvlparser-2.0.1.dist-info/WHEEL
uvlparser-2.0.1.dist-info/top_level.txt
uvlparser-2.0.1.dist-info/zip-safe
uvlparser-2.0.1.dist-info/RECORD
