Metadata-Version: 2.1
Name: uvlparser
Version: 2.0.1
Summary: This module provides a get_tree function to obtain an ANTLR parse-tree from a UVL-defined feature model
Home-page: https://github.com/Universal-Variability-Language/uvl-parser
Author: UVL Team
Author-email: jagalindo@us.es
License: GNU General Public License v3 (GPLv3)
Classifier: Programming Language :: Python :: 3
Classifier: License :: OSI Approved :: GNU General Public License v3 (GPLv3)
Classifier: Operating System :: OS Independent
Requires-Python: >=3.0
Requires-Dist: antlr4-python3-runtime==4.13.1
